Segunda_Fase_FPGA/Unidade_02/Cap_01/Simulacao/Atividade_Uni_02_Cap_01.sv
/*
 * @file Atividade_Uni_02_Cap_01.sv
 * @version 1.0
 * @date 17/08/2025
 * @author Manoel Felipe Costa Furtado
 * @copyright 2025 Manoel Furtado (MIT License) (veja LICENSE.md)
 * @brief Psistema de alarme simplificado
 *
 * @details
 * Módulo: alarme
 * Descrição: Implementa um sistema de alarme simplificado que é ativado
 * se pelo menos dois de três sensores estiverem ativos.
 * Entradas: A, B, C (sinais dos sensores)
 * Saída: Y (sinal de ativação do alarme)
 */
 
module alarme (
    input  wire A, // Entrada do sensor de porta
    input  wire B, // Entrada do sensor de janela
    input  wire C, // Entrada do sensor de presença
    output wire Y  // Saída para o LED do alarme
);

    // Fios (wires) intermediários para armazenar os resultados das
    // verificações de pares de sensores.
    wire AB, AC, BC;

    // Lógica Combinacional usando atribuições contínuas (assign)
    
    // A primeira porta AND verifica se os sensores A e B estão ativos
    assign AB = A & B;
    
    // A segunda porta AND verifica se os sensores A e C estão ativos
    assign AC = A & C;
    
    // A terceira porta AND verifica se os sensores B e C estão ativos
    assign BC = B & C;
    
    // A porta OR final combina os resultados. O alarme (Y) será ativado
    // se QUALQUER uma das condições anteriores (AB, AC ou BC) for verdadeira.
    assign Y = AB | AC | BC;
    
endmodule

Segunda_Fase_FPGA/Unidade_02/Cap_01/Simulacao/tb_Atividade_Uni_02_Cap_01.sv
module tb_Atividade_Uni_02_Cap_01;
logic a, b, c, y;
alarme uut(
    .A(a),
    .B(b),
    .C(c),
    .Y(y)
);

initial 
    begin
        $dumpfile("waveform.vcd");
        $dumpvars(0, tb_Atividade_Uni_02_Cap_01);
        //2^3 = 8
        a = 0; b = 0; c = 0;
        #5
        a = 0; b = 0; c = 1;
        #5
        a = 0; b = 1; c = 0;
        #5
        a = 0; b = 1; c = 1;
        #5
        a = 1; b = 0; c = 0;
        #5
        a = 1; b = 0; c = 1;
        #5
        a = 1; b = 1; c = 0;
        #5
        a = 1; b = 1; c = 1;
        #5;
        $finish;
    end
endmodule

// iverilog -g2012 -o tb_Atividade_Uni_02_Cap_01 Atividade_Uni_02_Cap_01.sv tb_Atividade_Uni_02_Cap_01.sv
// vvp tb_Atividade_Uni_02_Cap_01
// gtkwave waveform.vcd

Segunda_Fase_FPGA/Unidade_02/Cap_01/Simulacao/waveform.vcd
$date
	Sun Aug 17 18:07:02 2025
$end
$version
	Icarus Verilog
$end
$timescale
	1s
$end
$scope module tb_Atividade_Uni_02_Cap_01 $end
$var wire 1 ! y $end
$var reg 1 " a $end
$var reg 1 # b $end
$var reg 1 $ c $end
$scope module uut $end
$var wire 1 " A $end
$var wire 1 % AB $end
$var wire 1 & AC $end
$var wire 1 # B $end
$var wire 1 ' BC $end
$var wire 1 $ C $end
$var wire 1 ! Y $end
$upscope $end
$upscope $end
$enddefinitions $end
$comment Show the parameter values. $end
$dumpall
$end
#0
$dumpvars
0'
0&
0%
0$
0#
0"
0!
$end
#5
1$
#10
0$
1#
#15
1!
1'
1$
#20
0!
0'
0$
0#
1"
#25
1!
1&
1$
#30
0&
1%
0$
1#
#35
1&
1'
1$
