Segunda_Fase_FPGA/Unidade_07/Cap_01/src/design.sv
// ===================================================================
// Atividade: Unidade 07, Capítulo 01
// Arquivo:   design.sv
// Autor:     Manoel Felipe Costa Furtado
// Data:      05/10/2025
// Versão:    1.0
//
// Módulo:    adder_subtractor
// Descrição: Implementa um somador/subtrator completo de 1 bit.
//            O módulo calcula a soma (S) e o transporte de saída (Ts)
//            com base nas entradas A, B, um transporte de entrada (Te)
//            e um seletor de modo (M).
//
// Modo de Operação:
// - M = 0: Soma (A + B + Te) -> Ts é o Carry-Out
// - M = 1: Subtração (A - B - Te) -> Ts é o Borrow-Out
// ===================================================================

module adder_subtractor (
    input  logic M,      // Seletor de operação: 0=Soma, 1=Subtração
    input  logic A,      // Entrada (operando) A
    input  logic B,      // Entrada (operando) B
    input  logic Te,     // Transporte de Entrada (Carry-in / Borrow-in)
    output logic S,      // Saída da Soma/Diferença
    output logic Ts      // Saída de Transporte (Carry-out / Borrow-out)
);
    // A lógica da saída S (Soma/Diferença) é um XOR de 3 entradas,
    // sendo idêntica para a soma e a subtração de 1 bit.
    assign S = A ^ B ^ Te;

    // Sinais intermediários para maior clareza da lógica de Ts.
    logic carry_out;  // Armazena o resultado do carry-out da soma.
    logic borrow_out; // Armazena o resultado do borrow-out da subtração.

    // Implementa a lógica do Carry-Out de um somador completo.
    // Ocorre transporte de saída se pelo menos duas das entradas (A, B, Te) forem '1'.
    assign carry_out = (A & B) | (A & Te) | (B & Te);

    // Implementa a lógica do Borrow-Out de um subtrator completo.
    // Ocorre "empréstimo" de um bit se ~A&B, ou ~A&Te, ou B&Te.
    assign borrow_out = (~A & B) | (~A & Te) | (B & Te);

    // Multiplexador 2x1: Seleciona a saída Ts com base no modo M.
    // Se M for 0 (soma), a saída é carry_out.
    // Se M for 1 (subtração), a saída é borrow_out.
    assign Ts = (M == 0) ? carry_out : borrow_out;

endmodule

Segunda_Fase_FPGA/Unidade_07/Cap_01/src/testbench.sv
// ===================================================================
// Atividade: Unidade 07, Capítulo 01
// Arquivo:   testbench.sv
// Autor:     Manoel Felipe Costa Furtado
// Data:      05/10/2025
// Versão:    1.0
//
// Módulo:    testbench
// Descrição: Ambiente de verificação para o módulo 'adder_subtractor'.
//            Este testbench é auto-verificável ('self-checking'):
//            1. Gera automaticamente todas as 16 combinações de entrada.
//            2. Calcula internamente o resultado esperado ("golden model").
//            3. Compara a saída do DUT com o resultado esperado.
//            4. Reporta um erro detalhado se houver divergência.
// ===================================================================
`timescale 1ns/1ps

module testbench;
    // Sinais para conectar ao DUT (Device Under Test)
    logic M, A, B, Te;
    logic S, Ts;

    // Instanciação do Módulo sob Teste (Unit Under Test - UUT)
    adder_subtractor dut(.M(M), .A(A), .B(B), .Te(Te), .S(S), .Ts(Ts));

    // Bloco para configurar a geração do arquivo de formas de onda (VCD).
    initial begin
        $dumpfile("dump.vcd");
        $dumpvars(0, testbench); // Grava todas as variáveis deste módulo.
    end

    // Variáveis para o modelo de referência e controle dos loops.
    reg expS, expTs;
    integer m, a, b, te;

    // Bloco principal que gera os estímulos e verifica as saídas.
    initial begin
        // Cabeçalho para a saída no console.
        $display(" M A B Te | S Ts  (Resultado do DUT)");
        $display("----------|------------------------");

        // Loops aninhados para varrer todas as 16 combinações de entrada (2^4).
        for (int m=0; m<2; m++) begin
            for (int a=0; a<2; a++) begin
                for (int b=0; b<2; b++) begin
                    for (int te=0; te<2; te++) begin
                        // 1. Aplica os valores de entrada ao DUT.
                        M = m;
                        A = a; B = b; Te = te;

                        // Aguarda 1ns para a propagação dos sinais no DUT antes de verificar.
                        #1;

                        // 2. Calcula o resultado esperado (modelo de referência).
                        // A lógica esperada para S é um XOR de 3 entradas.
                        expS  = A ^ B ^ Te;
                        
                        // A lógica esperada para Ts depende do modo M.
                        // As expressões são idênticas às do design para consistência.
                        expTs = (M==1'b0) ? ((A & B) | (A & Te) | (B & Te)) // Carry-out esperado
                                          : ((~A & B) | (~A & Te) | (B & Te));   // Borrow-out esperado

                        // 3. Compara a saída do DUT com o resultado esperado e reporta erro se divergirem.
                        if (S !== expS || Ts !== expTs) begin
                            $error("ERRO! M=%b A=%b B=%b Te=%b | S=%b(exp:%b) Ts=%b(exp:%b)",
                                   M,A,B,Te, S,expS, Ts,expTs);
                        end

                        // Imprime os valores atuais do DUT no console para acompanhamento.
                        $display(" %1d %1d %1d %1d  | %1d %1d", M,A,B,Te,S,Ts);

                        // Aguarda mais 9ns para completar um ciclo de 10ns por vetor de teste.
                        // Isso cria uma forma de onda limpa e organizada no GTKWave.
                        #9;
                    end
                end
            end
        end
        
        $display("\nSimulacao concluida com sucesso. Nenhuma divergencia encontrada.");
        $finish;
    end
endmodule

Segunda_Fase_FPGA/Unidade_07/Cap_01/src/dump.vcd
$date
	Wed Oct 01 15:24:41 2025
$end
$version
	Icarus Verilog
$end
$timescale
	1ps
$end
$scope module testbench $end
$var wire 1 ! Ts $end
$var wire 1 " S $end
$var reg 1 # A $end
$var reg 1 $ B $end
$var reg 1 % M $end
$var reg 1 & Te $end
$var reg 1 ' expS $end
$var reg 1 ( expTs $end
$scope module dut $end
$var wire 1 # A $end
$var wire 1 $ B $end
$var wire 1 % M $end
$var wire 1 " S $end
$var wire 1 & Te $end
$var wire 1 ) borrow_out $end
$var wire 1 * carry_out $end
$var wire 1 ! Ts $end
$upscope $end
$scope begin $ivl_for_loop0 $end
$var integer 32 + m [31:0] $end
$scope begin $ivl_for_loop1 $end
$var integer 32 , a [31:0] $end
$scope begin $ivl_for_loop2 $end
$var integer 32 - b [31:0] $end
$scope begin $ivl_for_loop3 $end
$var integer 32 . te [31:0] $end
$upscope $end
$upscope $end
$upscope $end
$upscope $end
$upscope $end
$enddefinitions $end
$comment Show the parameter values. $end
$dumpall
$end
#0
$dumpvars
b0 .
b0 -
b0 ,
b0 +
0*
0)
x(
x'
0&
0%
0$
0#
0"
0!
$end
#1000
0(
0'
#10000
1)
1"
1&
b1 .
#11000
1'
#20000
0&
1$
b1 -
b0 .
#30000
1!
1*
0"
1&
b1 .
#31000
1(
0'
#40000
0!
0)
0*
1"
0&
0$
1#
b1 ,
b0 -
b0 .
#41000
0(
1'
#50000
1!
1*
0"
1&
b1 .
#51000
1(
0'
#60000
0&
1$
b1 -
b0 .
#70000
1)
1"
1&
b1 .
#71000
1'
#80000
0!
0*
0)
0"
0&
0$
0#
1%
b1 +
b0 ,
b0 -
b0 .
#81000
0(
0'
#90000
1!
1)
1"
1&
b1 .
#91000
1(
1'
#100000
0&
1$
b1 -
b0 .
#110000
1*
0"
1&
b1 .
#111000
0'
#120000
0!
0)
0*
1"
0&
0$
1#
b1 ,
b0 -
b0 .
#121000
0(
1'
#130000
1*
0"
1&
b1 .
#131000
0'
#140000
0&
1$
b1 -
b0 .
#150000
1!
1)
1"
1&
b1 .
#151000
1(
1'
#160000
b10 +
b10 ,
b10 -
b10 .
