Segunda_Fase_FPGA/Unidade_03/Cap_01/subtratorcompleto.v
/*
 * Atividade_Uni_02_Cap_02 
 * @file Atividade_Uni_02_Cap_02.sv
 * @version 1.0
 * @date 05/09/2025
 * @author Manoel Felipe Costa Furtado
 * @copyright 2025 Manoel Furtado (MIT License) (veja LICENSE.md)
 * @brief Subtrator Completo
 --------------------------------------------------------------------
   Módulo: subtratorcompleto
   Descrição: Representa um subtrator completo de 1 bit.
   Entradas: a, b, cin (borrow-in)
   Saídas: s (diferença), cout (borrow-out)
--------------------------------------------------------------------
*/
module subtratorcompleto(
    input a,
    input b,
    input cin,
    output s,
    output cout
);

    // Lógica para a saída de diferença (S)
    assign s = a ^ b ^ cin;

    // Lógica para a saída de empréstimo (Cout)
    // Cout é '1' quando precisamos "emprestar" do próximo bit.
    // Isso ocorre se (não A e B) ou (não A e Cin) ou (B e Cin).
    assign cout = (~a & b) | (~a & cin) | (b & cin);

endmodule

Segunda_Fase_FPGA/Unidade_02/Cap_02/subtratorcompleto_tb.v
/*
 * Atividade_Uni_02_Cap_02 
 * @file subtratorcompleto_tb.v
 * @version 1.0
 * @date 05/09/2025
 * @author Manoel Felipe Costa Furtado
 * @copyright 2025 Manoel Furtado (MIT License) (veja LICENSE.md)
 * @brief Subtrator Completo
--------------------------------------------------------------------
  Módulo: tb_subtratorcompleto
  Descrição: Testbench para o módulo subtratorcompleto.
--------------------------------------------------------------------
*/

`include "subtratorcompleto.v"
`timescale 1ns / 1ps // Define a unidade de tempo da simulação

module tb_subtratorcompleto;

    // 1. Declaração de sinais
    // Entradas para o DUT (Device Under Test) são do tipo 'reg'
    reg a_tb;
    reg b_tb;
    reg cin_tb;

    // Saídas do DUT são do tipo 'wire'
    wire s_tb;
    wire cout_tb;

    // 2. Instanciação do Módulo a ser testado (DUT)
    // Conecta os sinais do testbench às portas do módulo
    subtratorcompleto DUT (
        .a(a_tb),
        .b(b_tb),
        .cin(cin_tb),
        .s(s_tb),
        .cout(cout_tb)
    );

    // 3. Geração dos estímulos e controle da simulação
    initial begin
        // Configuração para gerar o arquivo de forma de onda (VCD)
        $dumpfile("subtratorcompleto.vcd");
        $dumpvars(0, tb_subtratorcompleto);

        // Mensagem inicial no console
        $display("Iniciando a simulacoo do Subtrator Completo...");
        $display("A B Cin | S Cout");
        $display("-------------------");

        // Casos de teste baseados na tabela verdade
        {a_tb, b_tb, cin_tb} = 3'b000; #10;
        {a_tb, b_tb, cin_tb} = 3'b001; #10;
        {a_tb, b_tb, cin_tb} = 3'b010; #10;
        {a_tb, b_tb, cin_tb} = 3'b011; #10;
        {a_tb, b_tb, cin_tb} = 3'b100; #10;
        {a_tb, b_tb, cin_tb} = 3'b101; #10;
        {a_tb, b_tb, cin_tb} = 3'b110; #10;
        {a_tb, b_tb, cin_tb} = 3'b111; #10;

        // Finaliza a simulação após o último caso de teste
        $display("Simulacao concluida.");
        $finish;
    end

    // Monitora as mudanças nos sinais e imprime no console
    // a cada mudança, formatando para se parecer com a tabela verdade.
    always @(a_tb, b_tb, cin_tb, s_tb, cout_tb) begin
        $monitor("%b %b %b   | %b %b", a_tb, b_tb, cin_tb, s_tb, cout_tb);
    end

endmodule

Segunda_Fase_FPGA/Unidade_03/Cap_01/subtratorcompleto.vcd
$date
	Thu Sep 04 22:29:12 2025
$end
$version
	Icarus Verilog
$end
$timescale
	1ps
$end
$scope module tb_subtratorcompleto $end
$var wire 1 ! s_tb $end
$var wire 1 " cout_tb $end
$var reg 1 # a_tb $end
$var reg 1 $ b_tb $end
$var reg 1 % cin_tb $end
$scope module DUT $end
$var wire 1 # a $end
$var wire 1 $ b $end
$var wire 1 % cin $end
$var wire 1 " cout $end
$var wire 1 ! s $end
$upscope $end
$upscope $end
$enddefinitions $end
$comment Show the parameter values. $end
$dumpall
$end
#0
$dumpvars
0%
0$
0#
0"
0!
$end
#10000
1"
1!
1%
#20000
1!
1$
0%
#30000
0!
1%
#40000
0"
1!
1#
0$
0%
#50000
0!
1%
#60000
0!
1$
0%
#70000
1"
1!
1%
