Segunda_Fase_FPGA/Unidade_03/Atividade_Em_Aula/Projeto_decodificador_3a8/decodificador_3a8.vhd
-- Este arquivo descreve um decodificador binário de 3 para 8.
-- Ele converte uma entrada binária de 3 bits em uma saída de 8 bits,
-- onde apenas um bit de saída é ativado por vez.
-- Possui também uma porta de habilitação (enable).

-- Inclusão da biblioteca padrão IEEE.
library IEEE;
-- Uso do pacote std_logic_1164, que define os tipos de dados padrão como std_logic.
use IEEE.std_logic_1164.all;

-- A ENTIDADE define a interface (as portas de entrada e saída) do componente.
entity decodificador_3a8 is
    port (
        -- 'sel' (select) é a entrada de 3 bits que determina qual saída será ativada.
        sel   : in std_logic_vector(2 downto 0);
        -- 'en' (enable) é a entrada de 1 bit que habilita ou desabilita o decodificador.
        en    : in std_logic;
        -- 'saida' é o barramento de 8 bits onde o resultado da decodificação aparece.
        saida : out std_logic_vector(7 downto 0)
    );
end decodificador_3a8;

-- A ARQUITETURA descreve o funcionamento interno do componente.
-- O estilo 'behavioral' ou comportamental descreve o comportamento através de processos e lógica sequencial.
architecture behavioral of decodificador_3a8 is
begin
    -- Um PROCESS é um bloco de código que é executado quando os sinais em sua
    -- lista de sensibilidade (neste caso, 'sel' e 'en') mudam de valor.
    process(sel, en)
    begin
        -- Verifica se o pino de habilitação 'en' está em nível lógico alto ('1').
        if en = '1' then
            -- Se estiver habilitado, um CASE é usado para avaliar o valor da entrada 'sel'.
            case sel is
                -- Para cada valor possível de 'sel', uma única saída correspondente é ativada.
                when "000" => saida <= "00000001"; -- Ativa a saída 0
                when "001" => saida <= "00000010"; -- Ativa a saída 1
                when "010" => saida <= "00000100"; -- Ativa a saída 2
                when "011" => saida <= "00001000"; -- Ativa a saída 3
                when "100" => saida <= "00010000"; -- Ativa a saída 4
                when "101" => saida <= "00100000"; -- Ativa a saída 5
                when "110" => saida <= "01000000"; -- Ativa a saída 6
                when "111" => saida <= "10000000"; -- Ativa a saída 7
                -- 'when others' é uma cláusula de segurança para cobrir quaisquer outros
                -- casos possíveis (útil para tipos de dados com mais estados, como std_ulogic).
                when others => saida <= (others => '0');
            end case;
        else
            -- Se o decodificador não estiver habilitado (en = '0'), todas as saídas
            -- são forçadas para o nível lógico baixo ('0').
            saida <= (others => '0');
        end if;
    end process;
end behavioral;

Segunda_Fase_FPGA/Unidade_04/Atividade_Em_Aula/Projeto_decodificador_3a8/tb_decodificador_3a8.vhd
-- Este arquivo é um Testbench, um código VHDL usado para simular e verificar
-- o funcionamento do componente 'decodificador_3a8'.

-- Inclusão da biblioteca padrão IEEE.
library IEEE;
-- Uso do pacote std_logic_1164.
use IEEE.std_logic_1164.all;

-- A ENTIDADE de um testbench é tipicamente vazia, pois ele não se conecta
-- a nenhum componente de nível superior.
entity tb_decodificador_3a8 is
end tb_decodificador_3a8;

-- A ARQUITETURA define o ambiente de teste.
architecture test of tb_decodificador_3a8 is
    -- Declaração de SINAIS internos que serão usados para conectar ao componente
    -- sob teste. Eles simulam os fios em uma placa de circuito.
    signal sel_tb : std_logic_vector(2 downto 0); -- Sinal para estimular a entrada 'sel'.
    signal en_tb  : std_logic;                   -- Sinal para estimular a entrada 'en'.
    signal saida_tb : std_logic_vector(7 downto 0); -- Sinal para observar a saída 'saida'.

    -- Declaração do COMPONENTE que será testado. A declaração deve ser
    -- idêntica à entidade do componente original.
    component decodificador_3a8
        port (
            sel   : in std_logic_vector(2 downto 0);
            en    : in std_logic;
            saida : out std_logic_vector(7 downto 0)
        );
    end component;
begin
    -- INSTANCIAÇÃO do componente sob teste (Unit Under Test - UUT).
    -- 'port map' conecta os sinais do testbench às portas do componente.
    uut: decodificador_3a8 port map (
        sel => sel_tb,
        en => en_tb,
        saida => saida_tb
    );

    -- Este PROCESS gera os estímulos (sinais de entrada) ao longo do tempo.
    -- Como não tem lista de sensibilidade, ele executa apenas uma vez no início da simulação.
    stim_proc: process
    begin
        -- 1. Inicia com o decodificador desabilitado para testar essa condição.
        en_tb <= '0';
        sel_tb <= "000";
        wait for 10 ns; -- Aguarda 10 nanosegundos.

        -- 2. Habilita o decodificador.
        en_tb <= '1';

        -- 3. Percorre todas as combinações de entrada possíveis para 'sel',
        --    mudando a cada 10 ns para que a mudança na saída possa ser observada.
        sel_tb <= "000"; wait for 10 ns;
        sel_tb <= "001"; wait for 10 ns;
        sel_tb <= "010"; wait for 10 ns;
        sel_tb <= "011"; wait for 10 ns;
        sel_tb <= "100"; wait for 10 ns;
        sel_tb <= "101"; wait for 10 ns;
        sel_tb <= "110"; wait for 10 ns;
        sel_tb <= "111"; wait for 10 ns;

        -- 4. Desabilita o decodificador novamente no final do teste.
        en_tb <= '0';
        wait for 10 ns;

        -- 'wait;' finaliza o processo de estímulo e suspende a simulação indefinidamente.
        wait;
    end process;
end test;

Segunda_Fase_FPGA/Unidade_03/Atividade_Em_Aula/Projeto_decodificador_3a8/decodificador.vcd
$date
  Wed Sep 03 10:44:55 2025
$end
$version
  GHDL v0
$end
$timescale
  1 fs
$end
$scope module standard $end
$upscope $end
$scope module std_logic_1164 $end
$upscope $end
$scope module tb_decodificador_3a8 $end
$var reg 3 ! sel_tb[2:0] $end
$var reg 1 " en_tb $end
$var reg 8 # saida_tb[7:0] $end
$scope module uut $end
$var reg 3 $ sel[2:0] $end
$var reg 1 % en $end
$var reg 8 & saida[7:0] $end
$upscope $end
$upscope $end
$enddefinitions $end
#0
b000 !
0"
b00000000 #
b000 $
0%
b00000000 &
#10000000
1"
b00000001 #
1%
b00000001 &
#20000000
b001 !
b00000010 #
b001 $
b00000010 &
#30000000
b010 !
b00000100 #
b010 $
b00000100 &
#40000000
b011 !
b00001000 #
b011 $
b00001000 &
#50000000
b100 !
b00010000 #
b100 $
b00010000 &
#60000000
b101 !
b00100000 #
b101 $
b00100000 &
#70000000
b110 !
b01000000 #
b110 $
b01000000 &
#80000000
b111 !
b10000000 #
b111 $
b10000000 &
#90000000
0"
b00000000 #
0%
b00000000 &
